{
  "math": {
    "1": {
      "description": "Grade 5 - Basic multiplication, division, simple fractions, foundational concepts",
      "questions": [
        {"question": "What is 7 × 8?", "answer": "56", "type": "input"},
        {"question": "What is 6 × 9?", "answer": "54", "type": "input"},
        {"question": "What is 8 × 7?", "answer": "56", "type": "input"},
        {"question": "What is 9 × 6?", "answer": "54", "type": "input"},
        {"question": "What is 7 × 6?", "answer": "42", "type": "input"},
        {"question": "What is 8 × 9?", "answer": "72", "type": "input"},
        {"question": "What is 6 × 7?", "answer": "42", "type": "input"},
        {"question": "What is 9 × 8?", "answer": "72", "type": "input"},
        {"question": "What is 7 × 7?", "answer": "49", "type": "input"},
        {"question": "What is 8 × 8?", "answer": "64", "type": "input"},
        {"question": "What is 9 × 9?", "answer": "81", "type": "input"},
        {"question": "What is 6 × 6?", "answer": "36", "type": "input"},
        {"question": "What is 12 × 5?", "answer": "60", "type": "input"},
        {"question": "What is 11 × 4?", "answer": "44", "type": "input"},
        {"question": "What is 12 × 3?", "answer": "36", "type": "input"},
        {"question": "What is 11 × 9?", "answer": "99", "type": "input"},
        {"question": "What is 12 × 4?", "answer": "48", "type": "input"},
        {"question": "What is 11 × 7?", "answer": "77", "type": "input"},
        {"question": "What is 12 × 6?", "answer": "72", "type": "input"},
        {"question": "What is 11 × 8?", "answer": "88", "type": "input"},
        {"question": "What is 42 ÷ 6?", "answer": "7", "type": "input"},
        {"question": "What is 56 ÷ 8?", "answer": "7", "type": "input"},
        {"question": "What is 72 ÷ 9?", "answer": "8", "type": "input"},
        {"question": "What is 48 ÷ 6?", "answer": "8", "type": "input"},
        {"question": "What is 54 ÷ 9?", "answer": "6", "type": "input"},
        {"question": "What is 63 ÷ 7?", "answer": "9", "type": "input"},
        {"question": "What is 64 ÷ 8?", "answer": "8", "type": "input"},
        {"question": "What is 81 ÷ 9?", "answer": "9", "type": "input"},
        {"question": "What is 36 ÷ 6?", "answer": "6", "type": "input"},
        {"question": "What is 49 ÷ 7?", "answer": "7", "type": "input"},
        {"question": "What is 1/2 of 10?", "answer": "5", "type": "input"},
        {"question": "What is 1/2 of 20?", "answer": "10", "type": "input"},
        {"question": "What is 1/2 of 30?", "answer": "15", "type": "input"},
        {"question": "What is 1/2 of 50?", "answer": "25", "type": "input"},
        {"question": "What is 1/2 of 100?", "answer": "50", "type": "input"},
        {"question": "What is 1/4 of 20?", "answer": "5", "type": "input"},
        {"question": "What is 1/4 of 40?", "answer": "10", "type": "input"},
        {"question": "What is 1/4 of 100?", "answer": "25", "type": "input"},
        {"question": "What is 1/4 of 80?", "answer": "20", "type": "input"},
        {"question": "What is 1/4 of 60?", "answer": "15", "type": "input"},
        {"question": "What is 1/3 of 9?", "answer": "3", "type": "input"},
        {"question": "What is 1/3 of 12?", "answer": "4", "type": "input"},
        {"question": "What is 1/3 of 30?", "answer": "10", "type": "input"},
        {"question": "What is 1/3 of 15?", "answer": "5", "type": "input"},
        {"question": "What is 1/3 of 21?", "answer": "7", "type": "input"},
        {"question": "What is 50 + 30?", "answer": "80", "type": "input"},
        {"question": "What is 70 + 40?", "answer": "110", "type": "input"},
        {"question": "What is 80 + 60?", "answer": "140", "type": "input"},
        {"question": "What is 90 + 70?", "answer": "160", "type": "input"},
        {"question": "What is 60 + 50?", "answer": "110", "type": "input"},
        {"question": "What is 100 - 30?", "answer": "70", "type": "input"},
        {"question": "What is 100 - 45?", "answer": "55", "type": "input"},
        {"question": "What is 100 - 65?", "answer": "35", "type": "input"},
        {"question": "What is 100 - 75?", "answer": "25", "type": "input"},
        {"question": "What is 100 - 15?", "answer": "85", "type": "input"},
        {"question": "What is 3 squared?", "answer": "9", "type": "input"},
        {"question": "What is 4 squared?", "answer": "16", "type": "input"},
        {"question": "What is 5 squared?", "answer": "25", "type": "input"},
        {"question": "What is 2 squared?", "answer": "4", "type": "input"},
        {"question": "What is 10 squared?", "answer": "100", "type": "input"},
        {"question": "What is double 25?", "answer": "50", "type": "input"},
        {"question": "What is double 45?", "answer": "90", "type": "input"},
        {"question": "What is double 35?", "answer": "70", "type": "input"},
        {"question": "What is double 15?", "answer": "30", "type": "input"},
        {"question": "What is double 55?", "answer": "110", "type": "input"},
        {"question": "What is half of 80?", "answer": "40", "type": "input"},
        {"question": "What is half of 60?", "answer": "30", "type": "input"},
        {"question": "What is half of 40?", "answer": "20", "type": "input"},
        {"question": "What is half of 70?", "answer": "35", "type": "input"},
        {"question": "What is half of 90?", "answer": "45", "type": "input"},
        {"question": "What is 5 × 5?", "answer": "25", "type": "input"},
        {"question": "What is 4 × 4?", "answer": "16", "type": "input"},
        {"question": "What is 3 × 3?", "answer": "9", "type": "input"},
        {"question": "What is 10 × 10?", "answer": "100", "type": "input"},
        {"question": "What is 2 × 2?", "answer": "4", "type": "input"},
        {"question": "What is 5 × 6?", "answer": "30", "type": "input"},
        {"question": "What is 4 × 7?", "answer": "28", "type": "input"},
        {"question": "What is 3 × 8?", "answer": "24", "type": "input"},
        {"question": "What is 5 × 9?", "answer": "45", "type": "input"},
        {"question": "What is 4 × 8?", "answer": "32", "type": "input"},
        {"question": "What is 30 ÷ 5?", "answer": "6", "type": "input"},
        {"question": "What is 28 ÷ 4?", "answer": "7", "type": "input"},
        {"question": "What is 24 ÷ 3?", "answer": "8", "type": "input"},
        {"question": "What is 45 ÷ 5?", "answer": "9", "type": "input"},
        {"question": "What is 32 ÷ 4?", "answer": "8", "type": "input"},
        {"question": "The formula for area of a rectangle is?", "answer": "length × width", "type": "multiple", "options": ["length × width", "length + width", "2 × (length + width)", "length ÷ width", "length - width"]},
        {"question": "The formula for perimeter of a rectangle is?", "answer": "2 × (length + width)", "type": "multiple", "options": ["2 × (length + width)", "length × width", "length + width", "4 × length", "2 × length × width"]},
        {"question": "The formula for area of a square is?", "answer": "side × side", "type": "multiple", "options": ["side × side", "4 × side", "2 × side", "side + side", "side ÷ 2"]},
        {"question": "The formula for perimeter of a square is?", "answer": "4 × side", "type": "multiple", "options": ["4 × side", "side × side", "2 × side", "side + 4", "side ÷ 4"]},
        {"question": "How many minutes in 1 hour?", "answer": "60", "type": "multiple", "options": ["60", "30", "100", "24", "120"]},
        {"question": "How many hours in 1 day?", "answer": "24", "type": "multiple", "options": ["24", "12", "60", "48", "36"]},
        {"question": "How many days in 1 week?", "answer": "7", "type": "multiple", "options": ["7", "5", "10", "14", "6"]},
        {"question": "How many months in 1 year?", "answer": "12", "type": "multiple", "options": ["12", "10", "52", "24", "365"]},
        {"question": "What is the order of operations acronym?", "answer": "PEMDAS", "type": "multiple", "options": ["PEMDAS", "BEDMAS", "BODMAS", "All of these", "SADMEP"]},
        {"question": "In PEMDAS, what does P stand for?", "answer": "Parentheses", "type": "multiple", "options": ["Parentheses", "Power", "Plus", "Product", "Prime"]},
        {"question": "What is a prime number?", "answer": "Only divisible by 1 and itself", "type": "multiple", "options": ["Only divisible by 1 and itself", "Any odd number", "Any even number", "Divisible by 2", "Less than 10"]},
        {"question": "Which is prime: 7, 8, 9, or 10?", "answer": "7", "type": "multiple", "options": ["7", "8", "9", "10", "None"]},
        {"question": "What is an even number?", "answer": "Divisible by 2", "type": "multiple", "options": ["Divisible by 2", "Ends in 1", "Any prime", "Not divisible by 2", "Greater than 10"]},
        {"question": "What is an odd number?", "answer": "Not divisible by 2", "type": "multiple", "options": ["Not divisible by 2", "Divisible by 2", "Any prime", "Ends in 0", "Less than 10"]},
        {"question": "Place value of 5 in 3542?", "answer": "500", "type": "multiple", "options": ["500", "50", "5", "5000", "0.5"]}
      ]
    },
    "2": {
      "description": "Grade 6 - Decimals, percentages, negative numbers, basic geometry",
      "questions": [
        {"question": "What is 0.5 × 10?", "answer": "5", "type": "input"},
        {"question": "What is 0.5 × 20?", "answer": "10", "type": "input"},
        {"question": "What is 0.25 × 20?", "answer": "5", "type": "input"},
        {"question": "What is 0.25 × 40?", "answer": "10", "type": "input"},
        {"question": "What is 0.1 × 50?", "answer": "5", "type": "input"},
        {"question": "What is 0.1 × 70?", "answer": "7", "type": "input"},
        {"question": "What is 0.2 × 30?", "answer": "6", "type": "input"},
        {"question": "What is 0.3 × 20?", "answer": "6", "type": "input"},
        {"question": "What is 0.75 × 8?", "answer": "6", "type": "input"},
        {"question": "What is 0.5 × 16?", "answer": "8", "type": "input"},
        {"question": "What is 10% of 50?", "answer": "5", "type": "input"},
        {"question": "What is 10% of 80?", "answer": "8", "type": "input"},
        {"question": "What is 10% of 120?", "answer": "12", "type": "input"},
        {"question": "What is 10% of 70?", "answer": "7", "type": "input"},
        {"question": "What is 10% of 150?", "answer": "15", "type": "input"},
        {"question": "What is 20% of 50?", "answer": "10", "type": "input"},
        {"question": "What is 20% of 100?", "answer": "20", "type": "input"},
        {"question": "What is 20% of 60?", "answer": "12", "type": "input"},
        {"question": "What is 20% of 80?", "answer": "16", "type": "input"},
        {"question": "What is 20% of 40?", "answer": "8", "type": "input"},
        {"question": "What is 25% of 40?", "answer": "10", "type": "input"},
        {"question": "What is 25% of 80?", "answer": "20", "type": "input"},
        {"question": "What is 25% of 100?", "answer": "25", "type": "input"},
        {"question": "What is 25% of 60?", "answer": "15", "type": "input"},
        {"question": "What is 25% of 20?", "answer": "5", "type": "input"},
        {"question": "What is 50% of 60?", "answer": "30", "type": "input"},
        {"question": "What is 50% of 90?", "answer": "45", "type": "input"},
        {"question": "What is 50% of 70?", "answer": "35", "type": "input"},
        {"question": "What is 50% of 110?", "answer": "55", "type": "input"},
        {"question": "What is 50% of 30?", "answer": "15", "type": "input"},
        {"question": "What is -5 + 8?", "answer": "3", "type": "input"},
        {"question": "What is -3 + 10?", "answer": "7", "type": "input"},
        {"question": "What is -7 + 12?", "answer": "5", "type": "input"},
        {"question": "What is -6 + 9?", "answer": "3", "type": "input"},
        {"question": "What is -4 + 11?", "answer": "7", "type": "input"},
        {"question": "What is 5 - 8?", "answer": "-3", "type": "input"},
        {"question": "What is 3 - 7?", "answer": "-4", "type": "input"},
        {"question": "What is 10 - 15?", "answer": "-5", "type": "input"},
        {"question": "What is 7 - 12?", "answer": "-5", "type": "input"},
        {"question": "What is 4 - 9?", "answer": "-5", "type": "input"},
        {"question": "What is -4 × 2?", "answer": "-8", "type": "input"},
        {"question": "What is -3 × 3?", "answer": "-9", "type": "input"},
        {"question": "What is -5 × 2?", "answer": "-10", "type": "input"},
        {"question": "What is -2 × 6?", "answer": "-12", "type": "input"},
        {"question": "What is -4 × 3?", "answer": "-12", "type": "input"},
        {"question": "What is -10 ÷ 2?", "answer": "-5", "type": "input"},
        {"question": "What is -15 ÷ 3?", "answer": "-5", "type": "input"},
        {"question": "What is -20 ÷ 4?", "answer": "-5", "type": "input"},
        {"question": "What is -18 ÷ 3?", "answer": "-6", "type": "input"},
        {"question": "What is -12 ÷ 4?", "answer": "-3", "type": "input"},
        {"question": "What is 13 × 5?", "answer": "65", "type": "input"},
        {"question": "What is 14 × 5?", "answer": "70", "type": "input"},
        {"question": "What is 15 × 4?", "answer": "60", "type": "input"},
        {"question": "What is 16 × 3?", "answer": "48", "type": "input"},
        {"question": "What is 12 × 7?", "answer": "84", "type": "input"},
        {"question": "What is 1/2 + 1/2?", "answer": "1", "type": "input"},
        {"question": "What is 1/4 + 1/4?", "answer": "1/2", "type": "input"},
        {"question": "What is 1/3 + 1/3?", "answer": "2/3", "type": "input"},
        {"question": "What is 1/5 + 1/5?", "answer": "2/5", "type": "input"},
        {"question": "What is 1/4 + 3/4?", "answer": "1", "type": "input"},
        {"question": "What is 3/4 - 1/4?", "answer": "1/2", "type": "input"},
        {"question": "What is 2/3 - 1/3?", "answer": "1/3", "type": "input"},
        {"question": "What is 4/5 - 2/5?", "answer": "2/5", "type": "input"},
        {"question": "What is 5/6 - 1/6?", "answer": "2/3", "type": "input"},
        {"question": "What is 7/8 - 3/8?", "answer": "1/2", "type": "input"},
        {"question": "What is 5.5 + 2.5?", "answer": "8", "type": "input"},
        {"question": "What is 7.5 + 2.5?", "answer": "10", "type": "input"},
        {"question": "What is 4.5 + 3.5?", "answer": "8", "type": "input"},
        {"question": "What is 6.5 + 1.5?", "answer": "8", "type": "input"},
        {"question": "What is 8.5 + 1.5?", "answer": "10", "type": "input"},
        {"question": "What is 9.5 - 4.5?", "answer": "5", "type": "input"},
        {"question": "What is 10.5 - 3.5?", "answer": "7", "type": "input"},
        {"question": "What is 8.5 - 2.5?", "answer": "6", "type": "input"},
        {"question": "What is 7.5 - 1.5?", "answer": "6", "type": "input"},
        {"question": "What is 12.5 - 2.5?", "answer": "10", "type": "input"},
        {"question": "What is 6 squared?", "answer": "36", "type": "input"},
        {"question": "What is 7 squared?", "answer": "49", "type": "input"},
        {"question": "What is 8 squared?", "answer": "64", "type": "input"},
        {"question": "What is 9 squared?", "answer": "81", "type": "input"},
        {"question": "What is 11 squared?", "answer": "121", "type": "input"},
        {"question": "What is 12 squared?", "answer": "144", "type": "input"},
        {"question": "Area of rectangle 5 × 8?", "answer": "40", "type": "input"},
        {"question": "Area of rectangle 6 × 7?", "answer": "42", "type": "input"},
        {"question": "Area of rectangle 4 × 9?", "answer": "36", "type": "input"},
        {"question": "Area of square with side 9?", "answer": "81", "type": "input"},
        {"question": "Perimeter of square with side 5?", "answer": "20", "type": "input"},
        {"question": "Perimeter of rectangle 3 × 4?", "answer": "14", "type": "input"},
        {"question": "Perimeter of rectangle 5 × 7?", "answer": "24", "type": "input"},
        {"question": "Formula for area of a triangle?", "answer": "(base × height) ÷ 2", "type": "multiple", "options": ["(base × height) ÷ 2", "base × height", "base + height", "(base + height) ÷ 2", "2 × base × height"]},
        {"question": "How to convert fraction to percent?", "answer": "Multiply by 100", "type": "multiple", "options": ["Multiply by 100", "Divide by 100", "Add 100", "Subtract 100", "Multiply by 10"]},
        {"question": "How to convert decimal to percent?", "answer": "Multiply by 100", "type": "multiple", "options": ["Multiply by 100", "Divide by 100", "Add 100", "Move decimal 1 place", "Square it"]},
        {"question": "What is the mean of a set of numbers?", "answer": "Sum divided by count", "type": "multiple", "options": ["Sum divided by count", "Middle number", "Most frequent", "Largest minus smallest", "Sum of all"]},
        {"question": "What is the median?", "answer": "Middle value when ordered", "type": "multiple", "options": ["Middle value when ordered", "Average", "Most frequent", "Difference", "Sum"]},
        {"question": "What is the mode?", "answer": "Most frequent value", "type": "multiple", "options": ["Most frequent value", "Average", "Middle value", "Range", "Sum"]},
        {"question": "What is the range?", "answer": "Max minus min", "type": "multiple", "options": ["Max minus min", "Average", "Middle value", "Most frequent", "Sum"]},
        {"question": "Formula for circumference of circle?", "answer": "2πr", "type": "multiple", "options": ["2πr", "πr²", "πd²", "2r", "r²"]},
        {"question": "Formula for area of circle?", "answer": "πr²", "type": "multiple", "options": ["πr²", "2πr", "πd", "2r²", "r³"]},
        {"question": "What is π approximately?", "answer": "3.14", "type": "multiple", "options": ["3.14", "3.41", "1.34", "4.13", "2.14"]},
        {"question": "Complementary angles add to?", "answer": "90°", "type": "multiple", "options": ["90°", "180°", "360°", "45°", "270°"]},
        {"question": "Supplementary angles add to?", "answer": "180°", "type": "multiple", "options": ["180°", "90°", "360°", "270°", "45°"]},
        {"question": "Angles in a triangle sum to?", "answer": "180°", "type": "multiple", "options": ["180°", "360°", "90°", "270°", "540°"]},
        {"question": "What type of angle is 90°?", "answer": "Right", "type": "multiple", "options": ["Right", "Acute", "Obtuse", "Straight", "Reflex"]},
        {"question": "What type of angle is less than 90°?", "answer": "Acute", "type": "multiple", "options": ["Acute", "Right", "Obtuse", "Straight", "Reflex"]}
      ]
    },
    "3": {
      "description": "Grade 7 - Basic algebra, ratios, proportions, integers",
      "questions": [
        {"question": "What is x if x + 5 = 12?", "answer": "7", "type": "input"},
        {"question": "What is x if x + 8 = 15?", "answer": "7", "type": "input"},
        {"question": "What is x if x - 3 = 10?", "answer": "13", "type": "input"},
        {"question": "What is x if x - 7 = 8?", "answer": "15", "type": "input"},
        {"question": "What is x if x + 6 = 14?", "answer": "8", "type": "input"},
        {"question": "What is x if 2x = 10?", "answer": "5", "type": "input"},
        {"question": "What is x if 3x = 15?", "answer": "5", "type": "input"},
        {"question": "What is x if 4x = 20?", "answer": "5", "type": "input"},
        {"question": "What is x if 5x = 30?", "answer": "6", "type": "input"},
        {"question": "What is x if 2x = 16?", "answer": "8", "type": "input"},
        {"question": "What is x if x/2 = 5?", "answer": "10", "type": "input"},
        {"question": "What is x if x/3 = 4?", "answer": "12", "type": "input"},
        {"question": "What is x if x/4 = 3?", "answer": "12", "type": "input"},
        {"question": "What is x if x/5 = 2?", "answer": "10", "type": "input"},
        {"question": "What is x if x/2 = 8?", "answer": "16", "type": "input"},
        {"question": "What is 15% of 40?", "answer": "6", "type": "input"},
        {"question": "What is 15% of 60?", "answer": "9", "type": "input"},
        {"question": "What is 30% of 50?", "answer": "15", "type": "input"},
        {"question": "What is 75% of 40?", "answer": "30", "type": "input"},
        {"question": "What is 40% of 25?", "answer": "10", "type": "input"},
        {"question": "What is 13 × 4?", "answer": "52", "type": "input"},
        {"question": "What is 14 × 3?", "answer": "42", "type": "input"},
        {"question": "What is 15 × 6?", "answer": "90", "type": "input"},
        {"question": "What is 16 × 4?", "answer": "64", "type": "input"},
        {"question": "What is 17 × 3?", "answer": "51", "type": "input"},
        {"question": "What is 18 × 5?", "answer": "90", "type": "input"},
        {"question": "What is 19 × 4?", "answer": "76", "type": "input"},
        {"question": "What is 21 × 3?", "answer": "63", "type": "input"},
        {"question": "What is 22 × 4?", "answer": "88", "type": "input"},
        {"question": "What is 23 × 3?", "answer": "69", "type": "input"},
        {"question": "What is 150 + 70?", "answer": "220", "type": "input"},
        {"question": "What is 180 + 40?", "answer": "220", "type": "input"},
        {"question": "What is 250 - 80?", "answer": "170", "type": "input"},
        {"question": "What is 300 - 120?", "answer": "180", "type": "input"},
        {"question": "What is 400 - 150?", "answer": "250", "type": "input"},
        {"question": "What is 1/2 + 1/4?", "answer": "3/4", "type": "input"},
        {"question": "What is 1/3 + 1/6?", "answer": "1/2", "type": "input"},
        {"question": "What is 2/3 + 1/6?", "answer": "5/6", "type": "input"},
        {"question": "What is 3/4 - 1/2?", "answer": "1/4", "type": "input"},
        {"question": "What is 5/6 - 1/3?", "answer": "1/2", "type": "input"},
        {"question": "The ratio 10:5 simplified?", "answer": "2:1", "type": "input"},
        {"question": "The ratio 15:5 simplified?", "answer": "3:1", "type": "input"},
        {"question": "The ratio 20:4 simplified?", "answer": "5:1", "type": "input"},
        {"question": "The ratio 12:4 simplified?", "answer": "3:1", "type": "input"},
        {"question": "The ratio 18:6 simplified?", "answer": "3:1", "type": "input"},
        {"question": "What is 180 ÷ 3?", "answer": "60", "type": "input"},
        {"question": "What is 240 ÷ 4?", "answer": "60", "type": "input"},
        {"question": "What is 150 ÷ 5?", "answer": "30", "type": "input"},
        {"question": "What is 210 ÷ 7?", "answer": "30", "type": "input"},
        {"question": "What is 360 ÷ 6?", "answer": "60", "type": "input"},
        {"question": "What is sqrt(49)?", "answer": "7", "type": "input"},
        {"question": "What is sqrt(64)?", "answer": "8", "type": "input"},
        {"question": "What is sqrt(81)?", "answer": "9", "type": "input"},
        {"question": "What is sqrt(100)?", "answer": "10", "type": "input"},
        {"question": "What is sqrt(121)?", "answer": "11", "type": "input"},
        {"question": "What is sqrt(144)?", "answer": "12", "type": "input"},
        {"question": "What is sqrt(169)?", "answer": "13", "type": "input"},
        {"question": "What is sqrt(36)?", "answer": "6", "type": "input"},
        {"question": "What is sqrt(25)?", "answer": "5", "type": "input"},
        {"question": "What is sqrt(16)?", "answer": "4", "type": "input"},
        {"question": "Area of triangle base 10 height 6?", "answer": "30", "type": "input"},
        {"question": "Area of triangle base 8 height 5?", "answer": "20", "type": "input"},
        {"question": "Area of triangle base 12 height 4?", "answer": "24", "type": "input"},
        {"question": "Area of triangle base 6 height 8?", "answer": "24", "type": "input"},
        {"question": "Area of triangle base 14 height 4?", "answer": "28", "type": "input"},
        {"question": "What is -8 + 15?", "answer": "7", "type": "input"},
        {"question": "What is -12 + 20?", "answer": "8", "type": "input"},
        {"question": "What is -10 + 18?", "answer": "8", "type": "input"},
        {"question": "What is -15 + 25?", "answer": "10", "type": "input"},
        {"question": "What is -9 + 14?", "answer": "5", "type": "input"},
        {"question": "What is 15 - 23?", "answer": "-8", "type": "input"},
        {"question": "What is 20 - 35?", "answer": "-15", "type": "input"},
        {"question": "What is 18 - 25?", "answer": "-7", "type": "input"},
        {"question": "What is 12 - 20?", "answer": "-8", "type": "input"},
        {"question": "What is 25 - 40?", "answer": "-15", "type": "input"},
        {"question": "Mean of 10, 20, 30?", "answer": "20", "type": "input"},
        {"question": "Mean of 5, 10, 15, 10?", "answer": "10", "type": "input"},
        {"question": "Mean of 2, 4, 6, 8?", "answer": "5", "type": "input"},
        {"question": "Mean of 10, 12, 14?", "answer": "12", "type": "input"},
        {"question": "Mean of 20, 30, 40?", "answer": "30", "type": "input"},
        {"question": "Median of 3, 5, 7?", "answer": "5", "type": "input"},
        {"question": "Median of 2, 4, 6, 8?", "answer": "5", "type": "input"},
        {"question": "Median of 10, 20, 30?", "answer": "20", "type": "input"},
        {"question": "Median of 1, 3, 5, 7, 9?", "answer": "5", "type": "input"},
        {"question": "Mode of 2, 3, 3, 4?", "answer": "3", "type": "input"},
        {"question": "What is (-2) × (-3)?", "answer": "6", "type": "input"},
        {"question": "What is (-4) × (-2)?", "answer": "8", "type": "input"},
        {"question": "What is (-5) × (-3)?", "answer": "15", "type": "input"},
        {"question": "What is (-3) × (-4)?", "answer": "12", "type": "input"},
        {"question": "What is (-6) × (-2)?", "answer": "12", "type": "input"},
        {"question": "Formula for simple interest?", "answer": "P × r × t", "type": "multiple", "options": ["P × r × t", "P + r + t", "P × r^t", "P/(r × t)", "P - r × t"]},
        {"question": "What is a unit rate?", "answer": "Rate per 1 unit", "type": "multiple", "options": ["Rate per 1 unit", "Total rate", "Average rate", "Maximum rate", "Minimum rate"]},
        {"question": "Cross multiply: a/b = c/d means?", "answer": "ad = bc", "type": "multiple", "options": ["ad = bc", "ab = cd", "ac = bd", "a + d = b + c", "a - b = c - d"]},
        {"question": "What is absolute value of -7?", "answer": "7", "type": "multiple", "options": ["7", "-7", "0", "14", "-14"]},
        {"question": "Distance formula on number line?", "answer": "|a - b|", "type": "multiple", "options": ["|a - b|", "a + b", "a × b", "a/b", "√(ab)"]},
        {"question": "Opposite of -5?", "answer": "5", "type": "multiple", "options": ["5", "-5", "0", "1/5", "-1/5"]},
        {"question": "What is scientific notation?", "answer": "a × 10^n form", "type": "multiple", "options": ["a × 10^n form", "Decimal form", "Fraction form", "Percentage", "Roman numerals"]},
        {"question": "Order of operations: what comes first?", "answer": "Parentheses", "type": "multiple", "options": ["Parentheses", "Addition", "Multiplication", "Subtraction", "Division"]},
        {"question": "Probability formula?", "answer": "Favorable/Total", "type": "multiple", "options": ["Favorable/Total", "Total/Favorable", "Favorable × Total", "Favorable + Total", "Favorable - Total"]},
        {"question": "What is a proportion?", "answer": "Two equal ratios", "type": "multiple", "options": ["Two equal ratios", "Single ratio", "Three ratios", "Percentage", "Fraction"]},
        {"question": "Scale factor formula?", "answer": "Image/Original", "type": "multiple", "options": ["Image/Original", "Original/Image", "Image + Original", "Image - Original", "Image × Original"]},
        {"question": "What makes a number rational?", "answer": "Can be written as fraction", "type": "multiple", "options": ["Can be written as fraction", "Has decimals", "Is negative", "Is positive", "Is whole"]}
      ]
    },
    "4": {
      "description": "Grade 8 - Linear equations, Pythagorean theorem, functions, exponents",
      "questions": [
        {"question": "What is x if 2x + 3 = 11?", "answer": "4", "type": "input"},
        {"question": "What is x if 3x - 2 = 13?", "answer": "5", "type": "input"},
        {"question": "What is x if 4x + 1 = 17?", "answer": "4", "type": "input"},
        {"question": "What is x if 5x - 5 = 20?", "answer": "5", "type": "input"},
        {"question": "What is x if 2x + 7 = 15?", "answer": "4", "type": "input"},
        {"question": "What is x if 3x + 4 = 19?", "answer": "5", "type": "input"},
        {"question": "What is x if 4x - 3 = 13?", "answer": "4", "type": "input"},
        {"question": "What is x if 6x - 6 = 30?", "answer": "6", "type": "input"},
        {"question": "What is x if 2x - 1 = 9?", "answer": "5", "type": "input"},
        {"question": "What is x if 5x + 2 = 27?", "answer": "5", "type": "input"},
        {"question": "Slope of y = 2x + 3?", "answer": "2", "type": "input"},
        {"question": "Slope of y = 3x - 5?", "answer": "3", "type": "input"},
        {"question": "Slope of y = -2x + 4?", "answer": "-2", "type": "input"},
        {"question": "Slope of y = 4x + 1?", "answer": "4", "type": "input"},
        {"question": "Slope of y = -x + 6?", "answer": "-1", "type": "input"},
        {"question": "Y-intercept of y = 2x + 5?", "answer": "5", "type": "input"},
        {"question": "Y-intercept of y = 3x - 4?", "answer": "-4", "type": "input"},
        {"question": "Y-intercept of y = x + 7?", "answer": "7", "type": "input"},
        {"question": "Y-intercept of y = -2x - 3?", "answer": "-3", "type": "input"},
        {"question": "Y-intercept of y = 5x?", "answer": "0", "type": "input"},
        {"question": "What is 2³?", "answer": "8", "type": "input"},
        {"question": "What is 3³?", "answer": "27", "type": "input"},
        {"question": "What is 4³?", "answer": "64", "type": "input"},
        {"question": "What is 5³?", "answer": "125", "type": "input"},
        {"question": "What is 2⁴?", "answer": "16", "type": "input"},
        {"question": "What is 2⁵?", "answer": "32", "type": "input"},
        {"question": "What is 10³?", "answer": "1000", "type": "input"},
        {"question": "What is 10⁴?", "answer": "10000", "type": "input"},
        {"question": "What is 3⁴?", "answer": "81", "type": "input"},
        {"question": "What is 4²?", "answer": "16", "type": "input"},
        {"question": "Triangle sides 3,4,c. What is c?", "answer": "5", "type": "input"},
        {"question": "Triangle sides 5,12,c. What is c?", "answer": "13", "type": "input"},
        {"question": "Triangle sides 8,6,c. What is c?", "answer": "10", "type": "input"},
        {"question": "Triangle sides 7,24,c. What is c?", "answer": "25", "type": "input"},
        {"question": "Triangle sides 9,12,c. What is c?", "answer": "15", "type": "input"},
        {"question": "Triangle sides 8,15,c. What is c?", "answer": "17", "type": "input"},
        {"question": "Triangle sides 20,21,c. What is c?", "answer": "29", "type": "input"},
        {"question": "Triangle sides 5,5,c where c is hypotenuse?", "answer": "7.07", "type": "multiple", "options": ["7.07", "10", "5", "25", "50"]},
        {"question": "What is 13²?", "answer": "169", "type": "input"},
        {"question": "What is 14²?", "answer": "196", "type": "input"},
        {"question": "What is 15²?", "answer": "225", "type": "input"},
        {"question": "What is 16²?", "answer": "256", "type": "input"},
        {"question": "What is 17²?", "answer": "289", "type": "input"},
        {"question": "What is 18²?", "answer": "324", "type": "input"},
        {"question": "What is 19²?", "answer": "361", "type": "input"},
        {"question": "What is 20²?", "answer": "400", "type": "input"},
        {"question": "What is sqrt(169)?", "answer": "13", "type": "input"},
        {"question": "What is sqrt(196)?", "answer": "14", "type": "input"},
        {"question": "What is sqrt(225)?", "answer": "15", "type": "input"},
        {"question": "What is sqrt(256)?", "answer": "16", "type": "input"},
        {"question": "What is sqrt(289)?", "answer": "17", "type": "input"},
        {"question": "What is sqrt(324)?", "answer": "18", "type": "input"},
        {"question": "What is sqrt(361)?", "answer": "19", "type": "input"},
        {"question": "What is sqrt(400)?", "answer": "20", "type": "input"},
        {"question": "Volume of cube side 4?", "answer": "64", "type": "input"},
        {"question": "Volume of cube side 5?", "answer": "125", "type": "input"},
        {"question": "Volume of cube side 3?", "answer": "27", "type": "input"},
        {"question": "Volume of cube side 6?", "answer": "216", "type": "input"},
        {"question": "Volume of cube side 2?", "answer": "8", "type": "input"},
        {"question": "Surface area of cube side 3?", "answer": "54", "type": "input"},
        {"question": "Surface area of cube side 4?", "answer": "96", "type": "input"},
        {"question": "Surface area of cube side 5?", "answer": "150", "type": "input"},
        {"question": "Surface area of cube side 2?", "answer": "24", "type": "input"},
        {"question": "What is 40% of 75?", "answer": "30", "type": "input"},
        {"question": "What is 60% of 50?", "answer": "30", "type": "input"},
        {"question": "What is 35% of 100?", "answer": "35", "type": "input"},
        {"question": "What is 45% of 80?", "answer": "36", "type": "input"},
        {"question": "What is 65% of 60?", "answer": "39", "type": "input"},
        {"question": "What is (-2)²?", "answer": "4", "type": "input"},
        {"question": "What is (-3)²?", "answer": "9", "type": "input"},
        {"question": "What is (-4)²?", "answer": "16", "type": "input"},
        {"question": "What is (-5)²?", "answer": "25", "type": "input"},
        {"question": "What is (-10)²?", "answer": "100", "type": "input"},
        {"question": "Scientific notation: 3000?", "answer": "3 × 10³", "type": "multiple", "options": ["3 × 10³", "3 × 10²", "30 × 10²", "0.3 × 10⁴", "3 × 10⁴"]},
        {"question": "Scientific notation: 45000?", "answer": "4.5 × 10⁴", "type": "multiple", "options": ["4.5 × 10⁴", "45 × 10³", "4.5 × 10³", "0.45 × 10⁵", "450 × 10²"]},
        {"question": "Scientific notation: 0.003?", "answer": "3 × 10⁻³", "type": "multiple", "options": ["3 × 10⁻³", "3 × 10³", "0.3 × 10⁻²", "30 × 10⁻⁴", "3 × 10⁻²"]},
        {"question": "Scientific notation: 0.0045?", "answer": "4.5 × 10⁻⁴", "type": "multiple", "options": ["4.5 × 10⁻⁴", "4.5 × 10⁻³", "45 × 10⁻⁵", "0.45 × 10⁻³", "4.5 × 10⁴"]},
        {"question": "Circumference of circle r=5?", "answer": "10π", "type": "multiple", "options": ["10π", "25π", "5π", "15π", "20π"]},
        {"question": "Area of circle r=5?", "answer": "25π", "type": "multiple", "options": ["25π", "10π", "5π", "50π", "15π"]},
        {"question": "Area of circle r=3?", "answer": "9π", "type": "multiple", "options": ["9π", "6π", "3π", "12π", "18π"]},
        {"question": "Circumference of circle r=7?", "answer": "14π", "type": "multiple", "options": ["14π", "49π", "7π", "21π", "28π"]},
        {"question": "What is f(3) if f(x) = 2x + 1?", "answer": "7", "type": "input"},
        {"question": "What is f(5) if f(x) = x² - 2?", "answer": "23", "type": "input"},
        {"question": "What is f(-2) if f(x) = 3x?", "answer": "-6", "type": "input"},
        {"question": "What is f(4) if f(x) = x² + x?", "answer": "20", "type": "input"},
        {"question": "The Pythagorean theorem is?", "answer": "a² + b² = c²", "type": "multiple", "options": ["a² + b² = c²", "a + b = c", "a² - b² = c²", "a × b = c", "a + b + c = 180"]},
        {"question": "Slope formula?", "answer": "(y₂-y₁)/(x₂-x₁)", "type": "multiple", "options": ["(y₂-y₁)/(x₂-x₁)", "(x₂-x₁)/(y₂-y₁)", "y₂ + y₁", "x₂ - x₁", "(y₂+y₁)/(x₂+x₁)"]},
        {"question": "Point-slope form?", "answer": "y - y₁ = m(x - x₁)", "type": "multiple", "options": ["y - y₁ = m(x - x₁)", "y = mx + b", "ax + by = c", "y = ax²", "x = my + b"]},
        {"question": "Standard form of a line?", "answer": "Ax + By = C", "type": "multiple", "options": ["Ax + By = C", "y = mx + b", "y - y₁ = m(x - x₁)", "x² + y² = r²", "y = ax² + bx + c"]},
        {"question": "What is a function?", "answer": "Each input has one output", "type": "multiple", "options": ["Each input has one output", "Each output has one input", "Multiple inputs per output", "No relation", "Random mapping"]},
        {"question": "Vertical line test checks for?", "answer": "If it's a function", "type": "multiple", "options": ["If it's a function", "If it's linear", "If it's quadratic", "If it's continuous", "If it's differentiable"]},
        {"question": "What are parallel lines?", "answer": "Same slope", "type": "multiple", "options": ["Same slope", "Negative reciprocal slopes", "Intersect at 90°", "Never straight", "Always vertical"]},
        {"question": "What are perpendicular lines?", "answer": "Negative reciprocal slopes", "type": "multiple", "options": ["Negative reciprocal slopes", "Same slope", "Parallel", "45° angle", "Never intersect"]},
        {"question": "Distance formula?", "answer": "√[(x₂-x₁)² + (y₂-y₁)²]", "type": "multiple", "options": ["√[(x₂-x₁)² + (y₂-y₁)²]", "(x₂-x₁) + (y₂-y₁)", "x₂ - x₁", "|x₂-x₁| + |y₂-y₁|", "(x₂+x₁)² + (y₂+y₁)²"]},
        {"question": "Midpoint formula?", "answer": "((x₁+x₂)/2, (y₁+y₂)/2)", "type": "multiple", "options": ["((x₁+x₂)/2, (y₁+y₂)/2)", "(x₂-x₁, y₂-y₁)", "(x₁×x₂, y₁×y₂)", "(x₁-x₂, y₁-y₂)", "√(x₁x₂), √(y₁y₂)"]},
        {"question": "What is an irrational number?", "answer": "Can't be written as fraction", "type": "multiple", "options": ["Can't be written as fraction", "Negative number", "Fraction", "Whole number", "Even number"]},
        {"question": "Example of irrational number?", "answer": "π", "type": "multiple", "options": ["π", "1/2", "0.5", "2/3", "-5"]}
      ]
    }
  },
  "5": {
    "description": "LEGENDARY TIER - Grade 9 with epic fantasy themes",
    "questions": [
      {"question": "A dragon flies in a circle radius 10m. Distance traveled in one loop?", "answer": "20π meters", "type": "multiple", "options": ["20π meters", "10π meters", "100π meters", "40π meters", "5π meters"]},
      {"question": "Your sword does 8 damage. With 150% critical hit, total damage?", "answer": "12", "type": "input"},
      {"question": "A wizard teleports 3 units east, 4 north. Distance from start?", "answer": "5", "type": "input"},
      {"question": "Your party of 4 splits 100 gold equally. Each gets?", "answer": "25", "type": "input"},
      {"question": "The ancient pyramid has square base 12, height 9. Volume?", "answer": "432", "type": "input"},
      {"question": "A phoenix flies at 30° angle. What is sin(30°)?", "answer": "0.5", "type": "input"},
      {"question": "The demon portal is a perfect circle area 100π. Radius?", "answer": "10", "type": "input"},
      {"question": "Castle tower 20m high casts shadow 20m. Sun's angle?", "answer": "45", "type": "input"},
      {"question": "The legendary blade multiplies power by i². Result?", "answer": "-1", "type": "input"},
      {"question": "Ancient rune shows 2⁹. Its power value?", "answer": "512", "type": "input"},
      {"question": "Mystic equation: factor x² - 49", "answer": "(x-7)(x+7)", "type": "multiple", "options": ["(x-7)(x+7)", "(x+7)²", "(x-49)", "(x-7)²", "(x+49)"]},
      {"question": "The Oracle's number √169 equals?", "answer": "13", "type": "input"},
      {"question": "Your quest: 3x + 5 = 20. Solve for x", "answer": "5", "type": "input"},
      {"question": "HP regenerates by y = 2x + 3. At x=5, HP gain?", "answer": "13", "type": "input"},
      {"question": "Treasure at coordinates (6,8). Distance from origin?", "answer": "10", "type": "input"},
      {"question": "Boss has 50% fire resistance. 30 fire damage becomes?", "answer": "15", "type": "input"},
      {"question": "Dragon's lair at (-5, 12). Distance from (0,0)?", "answer": "13", "type": "input"},
      {"question": "Spell power doubles every level: 2, 4, 8, 16, ?", "answer": "32", "type": "input"},
      {"question": "A paladin's shield blocks 75% of 40 damage. Damage taken?", "answer": "10", "type": "input"},
      {"question": "Mage spell: x² = 144. Positive value of x?", "answer": "12", "type": "input"},
      {"question": "Ranger shoots arrow at 45°. What is tan(45°)?", "answer": "1", "type": "input"},
      {"question": "Necromancer summons follow pattern 3, 9, 27. Next?", "answer": "81", "type": "input"},
      {"question": "Warrior's combo: 2x - 7 = 13. Solve for x", "answer": "10", "type": "input"},
      {"question": "Lightning spell branches: 1, 2, 4, 8. This is 2 to the power?", "answer": "n", "type": "multiple", "options": ["n", "2n", "n²", "n+1", "2n+1"]},
      {"question": "Potion heals 20% of 250 max HP. HP restored?", "answer": "50", "type": "input"},
      {"question": "Rogue moves 5 east, 12 north. Total distance?", "answer": "13", "type": "input"},
      {"question": "Ancient tablet: Factor x² - 64", "answer": "(x-8)(x+8)", "type": "multiple", "options": ["(x-8)(x+8)", "(x-8)²", "(x+8)²", "x(x-64)", "(x-32)(x+32)"]},
      {"question": "Wizard tower spiral staircase: sin(90°)?", "answer": "1", "type": "input"},
      {"question": "Demon's curse: -3 × -4 = ?", "answer": "12", "type": "input"},
      {"question": "Holy water heals √(225) HP. Amount?", "answer": "15", "type": "input"},
      {"question": "Archer's trajectory: vertex of y = -(x-3)² + 9 is?", "answer": "(3,9)", "type": "multiple", "options": ["(3,9)", "(3,-9)", "(-3,9)", "(9,3)", "(0,9)"]},
      {"question": "Barbarian rage multiplies damage by 3². Result?", "answer": "9", "type": "input"},
      {"question": "Cleric's blessing: 4x + 8 = 32. Find x", "answer": "6", "type": "input"},
      {"question": "Ice spell slows by 40%. Speed 50 becomes?", "answer": "30", "type": "input"},
      {"question": "Fire elemental: cos(0°) equals?", "answer": "1", "type": "input"},
      {"question": "Shadow step: teleport 7 west, 24 north. Distance?", "answer": "25", "type": "input"},
      {"question": "Legendary staff: 5³ charges. How many?", "answer": "125", "type": "input"},
      {"question": "Boss pattern: 2, 6, 18, 54. Next attack?", "answer": "162", "type": "input"},
      {"question": "Knight moves L-shape: 2 over, 1 up. Distance?", "answer": "√5", "type": "multiple", "options": ["√5", "3", "5", "√3", "2.5"]},
      {"question": "Vampire drains 15% of 200 HP. Amount drained?", "answer": "30", "type": "input"},
      {"question": "Portal equation x² + 6x + 9 factors to?", "answer": "(x+3)²", "type": "multiple", "options": ["(x+3)²", "(x-3)²", "(x+3)(x-3)", "(x+9)", "x²+9"]},
      {"question": "Golem's defense: cos(60°)?", "answer": "0.5", "type": "input"},
      {"question": "Lich's phylactery at point (8,15). Distance from origin?", "answer": "17", "type": "input"},
      {"question": "Monk's chi: sequence 5, 10, 20, 40. Pattern?", "answer": "×2", "type": "multiple", "options": ["×2", "+5", "×2+5", "2ⁿ", "+n"]},
      {"question": "Bard's song: f(x) = x² - 4. f(3) = ?", "answer": "5", "type": "input"},
      {"question": "Ranger trap: 30-60-90 triangle, short side 5, long side?", "answer": "10", "type": "input"},
      {"question": "Warlock pact: log₁₀(1000) = ?", "answer": "3", "type": "input"},
      {"question": "Druid shapeshift: bear has 125% of 80 HP. Total?", "answer": "100", "type": "input"},
      {"question": "Assassin strike: 6x - 12 = 30. Find x", "answer": "7", "type": "input"},
      {"question": "Titan's step covers 9 east, 40 north. Distance?", "answer": "41", "type": "input"},
      {"question": "Magic missile: i⁴ equals?", "answer": "1", "type": "input"},
      {"question": "Healing spring rate: y = 3x + 2. At x=4, heals?", "answer": "14", "type": "input"},
      {"question": "Dragon breath cone: tan(0°)?", "answer": "0", "type": "input"},
      {"question": "Cursed die: probability of rolling 6 on fair die?", "answer": "1/6", "type": "input"},
      {"question": "Skeleton army: 2⁸ undead. How many?", "answer": "256", "type": "input"},
      {"question": "Elven bow: Factor x² - 100", "answer": "(x-10)(x+10)", "type": "multiple", "options": ["(x-10)(x+10)", "(x-10)²", "(x+10)²", "x(x-100)", "(x-50)(x+50)"]},
      {"question": "Fortress wall: sin(60°)?", "answer": "√3/2", "type": "multiple", "options": ["√3/2", "1/2", "√2/2", "1", "0"]},
      {"question": "Minotaur maze: midpoint of (2,4) and (8,12)?", "answer": "(5,8)", "type": "multiple", "options": ["(5,8)", "(10,16)", "(6,8)", "(4,6)", "(3,4)"]},
      {"question": "Griffon flight path: 2⁶ = ?", "answer": "64", "type": "input"},
      {"question": "Alchemist formula: 5x + 10 = 40. Find x", "answer": "6", "type": "input"},
      {"question": "Frost armor reduces damage by 30%. 70 damage becomes?", "answer": "49", "type": "input"},
      {"question": "Lightning rod height 15m, shadow 20m. Distance from top to shadow end?", "answer": "25", "type": "input"},
      {"question": "Phoenix rebirth cycle: cos(180°)?", "answer": "-1", "type": "input"},
      {"question": "Treasure map: slope between (1,2) and (4,8)?", "answer": "2", "type": "input"},
      {"question": "Dwarf tunnel: 3⁴ = ?", "answer": "81", "type": "input"},
      {"question": "Spell scroll: Factor x² + 8x + 16", "answer": "(x+4)²", "type": "multiple", "options": ["(x+4)²", "(x-4)²", "(x+4)(x-4)", "(x+8)²", "(x+16)"]},
      {"question": "Ballista range: projectile at vertex (5,25) of parabola. Max height?", "answer": "25", "type": "input"},
      {"question": "Vampire bat swarm: √256 = ?", "answer": "16", "type": "input"},
      {"question": "Enchantment: 7x - 21 = 28. Find x", "answer": "7", "type": "input"},
      {"question": "Pegasus flight: rises 8m, flies forward 15m. Direct distance?", "answer": "17", "type": "input"},
      {"question": "Wizard duel: sin(270°)?", "answer": "-1", "type": "input"},
      {"question": "Goblin horde of 144. In 12×? formation", "answer": "12", "type": "input"},
      {"question": "Blessed weapon: 175% of base damage 20?", "answer": "35", "type": "input"},
      {"question": "Dungeon level -3 to level 5. Levels climbed?", "answer": "8", "type": "input"},
      {"question": "Magic circle radius 6. Circumference?", "answer": "12π", "type": "multiple", "options": ["12π", "36π", "6π", "18π", "24π"]},
      {"question": "Crystal formation: 5⁰ = ?", "answer": "1", "type": "input"},
      {"question": "Ranger's path: y = -2x + 10. Y-intercept?", "answer": "10", "type": "input"},
      {"question": "Demon lord HP: 10⁴ = ?", "answer": "10000", "type": "input"},
      {"question": "Catapult trajectory: Factor x² - 81", "answer": "(x-9)(x+9)", "type": "multiple", "options": ["(x-9)(x+9)", "(x-9)²", "(x+9)²", "(x-81)", "x(x-81)"]},
      {"question": "Monastery bell tower: tan(90°) is?", "answer": "undefined", "type": "multiple", "options": ["undefined", "1", "0", "∞", "-1"]},
      {"question": "Kraken tentacle reaches 20m east, 21m north. Distance?", "answer": "29", "type": "input"},
      {"question": "Mana potion restores 35% of 80 MP. Amount?", "answer": "28", "type": "input"},
      {"question": "Golem sequence: 4, 16, 64. Pattern?", "answer": "4ⁿ", "type": "multiple", "options": ["4ⁿ", "n⁴", "4n", "4+n", "n×4"]},
      {"question": "Warlock curse: 8x - 16 = 48. Find x", "answer": "8", "type": "input"},
      {"question": "Dragon scale armor: √324 defense rating?", "answer": "18", "type": "input"},
      {"question": "Teleportation: from (3,4) to (9,12). Distance?", "answer": "10", "type": "input"},
      {"question": "Divine blessing: cos(270°)?", "answer": "0", "type": "input"},
      {"question": "Necromancer's equation: x² = 196. Positive x?", "answer": "14", "type": "input"},
      {"question": "Elemental fusion: (-5)² = ?", "answer": "25", "type": "input"},
      {"question": "Thieves guild code: 11² = ?", "answer": "121", "type": "input"},
      {"question": "Portal coordinates form right triangle 10,24,c. Find c", "answer": "26", "type": "input"},
      {"question": "Berserker rage: 225% of 40 damage?", "answer": "90", "type": "input"},
      {"question": "Dungeon trap: 9x + 18 = 90. Find x", "answer": "8", "type": "input"},
      {"question": "Wizard familiar flies pattern: sin²θ + cos²θ = ?", "answer": "1", "type": "input"},
      {"question": "Epic quest reward: 2¹⁰ gold. How much?", "answer": "1024", "type": "input"},
      {"question": "Dragon's age: √400 decades?", "answer": "20", "type": "input"},
      {"question": "Legendary shield blocks x² - 121 damage. Factor this", "answer": "(x-11)(x+11)", "type": "multiple", "options": ["(x-11)(x+11)", "(x-11)²", "(x+11)²", "x(x-121)", "(x-60.5)(x+60.5)"]},
      {"question": "Celestial alignment: What is i² + 1?", "answer": "0", "type": "input"},
      {"question": "Demon's riddle: If 3ˣ = 81, what is x?", "answer": "4", "type": "input"},
      {"question": "Hero's journey: Travel 12 north, 35 east. Total distance?", "answer": "37", "type": "input"},
      {"question": "Ancient prophecy: The sum of angles in any triangle?", "answer": "180", "type": "input"},
      {"question": "Dragon's treasure: 45% of 1200 gold?", "answer": "540", "type": "input"},
      {"question": "Mystic portal shape: Area of circle radius 8?", "answer": "64π", "type": "multiple", "options": ["64π", "16π", "8π", "32π", "128π"]},
      {"question": "Final boss HP: 15³ = ?", "answer": "3375", "type": "input"}
    ]
  }
}